mbonig/wakeywakey/__init__.py
mbonig/wakeywakey/py.typed
mbonig/wakeywakey/_jsii/__init__.py
mbonig/wakeywakey/_jsii/wakeywakey@1.89.2.jsii.tgz
mbonig.wakeywakey-1.89.2.dist-info/METADATA
mbonig.wakeywakey-1.89.2.dist-info/WHEEL
mbonig.wakeywakey-1.89.2.dist-info/top_level.txt
mbonig.wakeywakey-1.89.2.dist-info/RECORD
