Metadata-Version: 2.1
Name: mbonig.wakeywakey
Version: 1.89.2
Summary: A CDK construct that will automatically start a stopped EC2 instance at a given time.
Home-page: https://github.com/mbonig/wakeywakey
Author: Matthew Bonig<matthew.bonig@gmail.com>
License: Apache-2.0
Project-URL: Source, https://github.com/mbonig/wakeywakey
Platform: UNKNOWN
Classifier: Intended Audience :: Developers
Classifier: Operating System :: OS Independent
Classifier: Programming Language :: JavaScript
Classifier: Programming Language :: Python :: 3 :: Only
Classifier: Programming Language :: Python :: 3.6
Classifier: Programming Language :: Python :: 3.7
Classifier: Programming Language :: Python :: 3.8
Classifier: Programming Language :: Python :: 3.9
Classifier: Typing :: Typed
Classifier: Development Status :: 5 - Production/Stable
Classifier: License :: OSI Approved
Requires-Python: >=3.6
Requires-Dist: aws-cdk.aws-ec2 (<2.0.0,>=1.89.0)
Requires-Dist: aws-cdk.aws-events-targets (<2.0.0,>=1.89.0)
Requires-Dist: aws-cdk.aws-events (<2.0.0,>=1.89.0)
Requires-Dist: aws-cdk.aws-iam (<2.0.0,>=1.89.0)
Requires-Dist: aws-cdk.aws-lambda-nodejs (<2.0.0,>=1.89.0)
Requires-Dist: aws-cdk.aws-lambda (<2.0.0,>=1.89.0)
Requires-Dist: aws-cdk.core (<2.0.0,>=1.89.0)
Requires-Dist: cdk-iam-floyd (==0.120.0)
Requires-Dist: constructs (<4.0.0,>=3.2.27)
Requires-Dist: jsii (<2.0.0,>=1.16.0)
Requires-Dist: publication (>=0.0.3)
